wisecube_sdk/__init__.py
wisecube_sdk/api_calls.py
wisecube_sdk/client.py
wisecube_sdk/create_payload.py
wisecube_sdk/create_response.py
wisecube_sdk/model_formats.py
wisecube_sdk/node_types.py
wisecube_sdk/string_query.py
wisecube-1.1.1.dist-info/LICENSE
wisecube-1.1.1.dist-info/METADATA
wisecube-1.1.1.dist-info/WHEEL
wisecube-1.1.1.dist-info/top_level.txt
wisecube-1.1.1.dist-info/RECORD
