Metadata-Version: 2.1
Name: wisecube
Version: 1.1.1
Summary: Wisecube SDK for graph Search
Home-page: https://github.com/wisecubeai/wisecube-python-sdk
Author: Wisecube
Author-email: info@wisecube.ai
License: UNKNOWN
Platform: UNKNOWN
Classifier: Programming Language :: Python :: 3
Classifier: License :: OSI Approved :: MIT License
Classifier: Operating System :: OS Independent
Requires-Python: >=3.6
License-File: LICENSE
Requires-Dist: pandas==1.5.3
Requires-Dist: requests==2.31.0
Requires-Dist: numpy==1.26.4
Requires-Dist: tqdm==4.67.1
Provides-Extra: pandas
Requires-Dist: pandas==1.5.3; extra == "pandas"
